silverscreen/__init__.py
silverscreen/camera/__init__.py
silverscreen/camera/camera_base.py
silverscreen/camera/camera_oak.py
silverscreen/camera/camera_realsense.py
silverscreen/camera/camera_zed.py
silverscreen/camera/utils.py
silverscreen/constants.py
silverscreen/data_collection.py
silverscreen/deploy.py
silverscreen/filters.py
silverscreen/hands.py
silverscreen/main.py
silverscreen/playback.py
silverscreen/player.py
silverscreen/preprocess.py
silverscreen/retarget/hand.py
silverscreen/retarget/robot.py
silverscreen/retarget/robot_wrapper.py
silverscreen/state_machine.py
silverscreen/television.py
silverscreen/upsampler.py
silverscreen/utils.py
silverscreen/webrtc/__init__.py
silverscreen/webrtc/client.js
silverscreen/webrtc/index.html
silverscreen/webrtc/zed_server.py
teleoperation-0.3.0.dist-info/METADATA
teleoperation-0.3.0.dist-info/WHEEL
teleoperation-0.3.0.dist-info/entry_points.txt
teleoperation-0.3.0.dist-info/licenses/LICENSE
teleoperation-0.3.0.dist-info/RECORD
