Metadata-Version: 2.1
Name: teleoperation
Version: 0.3.0
Summary: Teleoperation for Fourier Robots
Author-Email: Yuxiang Gao <yuxiang.gao@fftai.com>
License: MIT
Requires-Python: <3.12,~=3.10
Requires-Dist: numpy~=1.26.4
Requires-Dist: h5py>=3.11.0
Requires-Dist: pytransform3d>=3.6.2
Requires-Dist: vuer[all]==0.0.32rc8
Requires-Dist: tqdm>=4.66.5
Requires-Dist: rich>=13.8.1
Requires-Dist: opencv-python>=4.10.0.84
Requires-Dist: opencv-contrib-python>=4.10.0.84
Requires-Dist: pynput>=1.7.7
Requires-Dist: loguru>=0.7.2
Requires-Dist: typer>=0.12.5
Requires-Dist: omegaconf>=2.3.0
Requires-Dist: torch~=2.4.1
Requires-Dist: torchvision~=0.19.1
Requires-Dist: dex-retargeting==0.4.5
Requires-Dist: pin-pink>=3.0.0
Requires-Dist: rerun-sdk>=0.18.2
Requires-Dist: meshcat>=0.3.2
Requires-Dist: meshcat-shapes>=0.3.0
Requires-Dist: numba>=0.60.0
Requires-Dist: pillow>=11.0.0
Requires-Dist: hydra-core>=1.3.2
Requires-Dist: hydra-colorlog>=1.2.0
Provides-Extra: webrtc
Requires-Dist: aiortc>=1.9.0; extra == "webrtc"
Requires-Dist: aiohttp>=3.10.5; extra == "webrtc"
Requires-Dist: aiohttp-cors>=0.7.0; extra == "webrtc"
Requires-Dist: av>=12.3.0; extra == "webrtc"
Provides-Extra: realsense
Requires-Dist: pyrealsense2>=2.55.1.6486; extra == "realsense"
Provides-Extra: fourier
Requires-Dist: fourier-grx-client==0.2.0a8; extra == "fourier"
Requires-Dist: fourier-dhx>=0.0.2; extra == "fourier"
Provides-Extra: depthai
Requires-Dist: depthai-sdk>=1.15.0; extra == "depthai"
Requires-Dist: av>=13.1.0; extra == "depthai"
